janehag/__init__.py
janehag/logging.py
janehag/snowflake.py
janehag/aws/__init__.py
janehag/aws/rds.py
janehag/aws/s3.py
janehag-0.1.1.dist-info/LICENSE
janehag-0.1.1.dist-info/METADATA
janehag-0.1.1.dist-info/WHEEL
janehag-0.1.1.dist-info/top_level.txt
janehag-0.1.1.dist-info/RECORD
