Metadata-Version: 2.1
Name: janehag
Version: 0.1.1
Summary: SE Libary for various tasks
Home-page: UNKNOWN
Author: KasperJanehag
Author-email: kasper.janehag@gmail.com
License: MIT
Platform: UNKNOWN
Classifier: License :: OSI Approved :: MIT License
Classifier: Programming Language :: Python :: 3
Classifier: Programming Language :: Python :: 3.7
Requires-Dist: pandas (>=1.1.1)
Requires-Dist: boto3 (>=1.14.15)
Requires-Dist: tables
Requires-Dist: numpy (>=1.19.0)
Requires-Dist: psycopg2-binary
Requires-Dist: sqlalchemy
Requires-Dist: plotly
Requires-Dist: h5py
Requires-Dist: s3fs
Requires-Dist: colorama
Requires-Dist: snowflake
Requires-Dist: snowflake-connector-python
Requires-Dist: snowflake.sqlalchemy
